<?xml version="1.0" encoding="UTF-8"?>
<!--
Created with Funkin Packer v0.1.3 https://neeeoo.github.io/funkin-packer/
-->
<TextureAtlas imagePath="titleEnter.png" width="1258" height="1991">
	<SubTexture name="ENTER PRESSED0001" x="1" y="1" width="1256" height="73" frameX="-105" frameY="-0" frameWidth="1478" frameHeight="78"/>
	<SubTexture name="ENTER PRESSED0002" x="1" y="77" width="1256" height="73" frameX="-105" frameY="-0" frameWidth="1478" frameHeight="78"/>
	<SubTexture name="ENTER PRESSED0003" x="1" y="1" width="1256" height="73" frameX="-105" frameY="-0" frameWidth="1478" frameHeight="78"/>
	<SubTexture name="ENTER PRESSED0004" x="1" y="77" width="1256" height="73" frameX="-105" frameY="-0" frameWidth="1478" frameHeight="78"/>
	<SubTexture name="ENTER PRESSED0005" x="1" y="1" width="1256" height="73" frameX="-105" frameY="-0" frameWidth="1478" frameHeight="78"/>
	<SubTexture name="ENTER PRESSED0006" x="1" y="77" width="1256" height="73" frameX="-105" frameY="-0" frameWidth="1478" frameHeight="78"/>
	<SubTexture name="ENTER PRESSED0007" x="1" y="1" width="1256" height="73" frameX="-105" frameY="-0" frameWidth="1478" frameHeight="78"/>
	<SubTexture name="ENTER PRESSED0008" x="1" y="77" width="1256" height="73" frameX="-105" frameY="-0" frameWidth="1478" frameHeight="78"/>
	<SubTexture name="Press Enter to Begin0001" x="1" y="153" width="1255" height="77" frameX="-112" frameY="-3" frameWidth="1494" frameHeight="96"/>
	<SubTexture name="Press Enter to Begin0002" x="1" y="233" width="1255" height="77" frameX="-112" frameY="-3" frameWidth="1494" frameHeight="96"/>
	<SubTexture name="Press Enter to Begin0003" x="1" y="313" width="1255" height="77" frameX="-112" frameY="-3" frameWidth="1494" frameHeight="96"/>
	<SubTexture name="Press Enter to Begin0004" x="1" y="393" width="1255" height="77" frameX="-112" frameY="-3" frameWidth="1494" frameHeight="96"/>
	<SubTexture name="Press Enter to Begin0005" x="1" y="473" width="1255" height="77" frameX="-112" frameY="-3" frameWidth="1494" frameHeight="96"/>
	<SubTexture name="Press Enter to Begin0006" x="1" y="553" width="1255" height="77" frameX="-112" frameY="-3" frameWidth="1494" frameHeight="96"/>
	<SubTexture name="Press Enter to Begin0007" x="1" y="633" width="1255" height="77" frameX="-112" frameY="-3" frameWidth="1494" frameHeight="96"/>
	<SubTexture name="Press Enter to Begin0008" x="1" y="713" width="1255" height="77" frameX="-112" frameY="-3" frameWidth="1494" frameHeight="96"/>
	<SubTexture name="Press Enter to Begin0009" x="1" y="793" width="1255" height="77" frameX="-112" frameY="-3" frameWidth="1494" frameHeight="96"/>
	<SubTexture name="Press Enter to Begin0010" x="1" y="873" width="1255" height="77" frameX="-112" frameY="-3" frameWidth="1494" frameHeight="96"/>
	<SubTexture name="Press Enter to Begin0011" x="1" y="953" width="1255" height="77" frameX="-112" frameY="-3" frameWidth="1494" frameHeight="96"/>
	<SubTexture name="Press Enter to Begin0012" x="1" y="1033" width="1255" height="77" frameX="-112" frameY="-3" frameWidth="1494" frameHeight="96"/>
	<SubTexture name="Press Enter to Begin0013" x="1" y="1113" width="1255" height="77" frameX="-112" frameY="-3" frameWidth="1494" frameHeight="96"/>
	<SubTexture name="Press Enter to Begin0014" x="1" y="1193" width="1255" height="77" frameX="-112" frameY="-3" frameWidth="1494" frameHeight="96"/>
	<SubTexture name="Press Enter to Begin0015" x="1" y="1273" width="1255" height="77" frameX="-112" frameY="-3" frameWidth="1494" frameHeight="96"/>
	<SubTexture name="Press Enter to Begin0016" x="1" y="1353" width="1255" height="77" frameX="-112" frameY="-3" frameWidth="1494" frameHeight="96"/>
	<SubTexture name="Press Enter to Begin0017" x="1" y="1433" width="1255" height="77" frameX="-112" frameY="-3" frameWidth="1494" frameHeight="96"/>
	<SubTexture name="Press Enter to Begin0018" x="1" y="1513" width="1255" height="77" frameX="-112" frameY="-3" frameWidth="1494" frameHeight="96"/>
	<SubTexture name="Press Enter to Begin0019" x="1" y="1593" width="1255" height="77" frameX="-112" frameY="-3" frameWidth="1494" frameHeight="96"/>
	<SubTexture name="Press Enter to Begin0020" x="1" y="1673" width="1255" height="77" frameX="-112" frameY="-3" frameWidth="1494" frameHeight="96"/>
	<SubTexture name="Press Enter to Begin0021" x="1" y="1753" width="1255" height="77" frameX="-112" frameY="-3" frameWidth="1494" frameHeight="96"/>
	<SubTexture name="Press Enter to Begin0022" x="1" y="1833" width="1255" height="77" frameX="-112" frameY="-3" frameWidth="1494" frameHeight="96"/>
	<SubTexture name="Press Enter to Begin0023" x="1" y="1913" width="1255" height="77" frameX="-112" frameY="-3" frameWidth="1494" frameHeight="96"/>
	<SubTexture name="Press Enter to Begin0024" x="1" y="1913" width="1255" height="77" frameX="-112" frameY="-3" frameWidth="1494" frameHeight="96"/>
	<SubTexture name="Press Enter to Begin0025" x="1" y="1833" width="1255" height="77" frameX="-112" frameY="-3" frameWidth="1494" frameHeight="96"/>
	<SubTexture name="Press Enter to Begin0026" x="1" y="1753" width="1255" height="77" frameX="-112" frameY="-3" frameWidth="1494" frameHeight="96"/>
	<SubTexture name="Press Enter to Begin0027" x="1" y="1673" width="1255" height="77" frameX="-112" frameY="-3" frameWidth="1494" frameHeight="96"/>
	<SubTexture name="Press Enter to Begin0028" x="1" y="1593" width="1255" height="77" frameX="-112" frameY="-3" frameWidth="1494" frameHeight="96"/>
	<SubTexture name="Press Enter to Begin0029" x="1" y="1513" width="1255" height="77" frameX="-112" frameY="-3" frameWidth="1494" frameHeight="96"/>
	<SubTexture name="Press Enter to Begin0030" x="1" y="1433" width="1255" height="77" frameX="-112" frameY="-3" frameWidth="1494" frameHeight="96"/>
	<SubTexture name="Press Enter to Begin0031" x="1" y="1353" width="1255" height="77" frameX="-112" frameY="-3" frameWidth="1494" frameHeight="96"/>
	<SubTexture name="Press Enter to Begin0032" x="1" y="1273" width="1255" height="77" frameX="-112" frameY="-3" frameWidth="1494" frameHeight="96"/>
	<SubTexture name="Press Enter to Begin0033" x="1" y="1193" width="1255" height="77" frameX="-112" frameY="-3" frameWidth="1494" frameHeight="96"/>
	<SubTexture name="Press Enter to Begin0034" x="1" y="1113" width="1255" height="77" frameX="-112" frameY="-3" frameWidth="1494" frameHeight="96"/>
	<SubTexture name="Press Enter to Begin0035" x="1" y="1033" width="1255" height="77" frameX="-112" frameY="-3" frameWidth="1494" frameHeight="96"/>
	<SubTexture name="Press Enter to Begin0036" x="1" y="953" width="1255" height="77" frameX="-112" frameY="-3" frameWidth="1494" frameHeight="96"/>
	<SubTexture name="Press Enter to Begin0037" x="1" y="873" width="1255" height="77" frameX="-112" frameY="-3" frameWidth="1494" frameHeight="96"/>
	<SubTexture name="Press Enter to Begin0038" x="1" y="793" width="1255" height="77" frameX="-112" frameY="-3" frameWidth="1494" frameHeight="96"/>
	<SubTexture name="Press Enter to Begin0039" x="1" y="713" width="1255" height="77" frameX="-112" frameY="-3" frameWidth="1494" frameHeight="96"/>
	<SubTexture name="Press Enter to Begin0040" x="1" y="633" width="1255" height="77" frameX="-112" frameY="-3" frameWidth="1494" frameHeight="96"/>
	<SubTexture name="Press Enter to Begin0041" x="1" y="553" width="1255" height="77" frameX="-112" frameY="-3" frameWidth="1494" frameHeight="96"/>
	<SubTexture name="Press Enter to Begin0042" x="1" y="473" width="1255" height="77" frameX="-112" frameY="-3" frameWidth="1494" frameHeight="96"/>
	<SubTexture name="Press Enter to Begin0043" x="1" y="393" width="1255" height="77" frameX="-112" frameY="-3" frameWidth="1494" frameHeight="96"/>
	<SubTexture name="Press Enter to Begin0044" x="1" y="313" width="1255" height="77" frameX="-112" frameY="-3" frameWidth="1494" frameHeight="96"/>
	<SubTexture name="Press Enter to Begin0045" x="1" y="233" width="1255" height="77" frameX="-112" frameY="-3" frameWidth="1494" frameHeight="96"/>
	<SubTexture name="Press Enter to Begin0046" x="1" y="153" width="1255" height="77" frameX="-112" frameY="-3" frameWidth="1494" frameHeight="96"/>
</TextureAtlas>